sqrl/__init__.py
sqrl/core.py
sqrl/parser.py
sqrl/utils.py
sqrl-0.2.0.dist-info/LICENSE
sqrl-0.2.0.dist-info/METADATA
sqrl-0.2.0.dist-info/WHEEL
sqrl-0.2.0.dist-info/top_level.txt
sqrl-0.2.0.dist-info/RECORD
