Metadata-Version: 2.1
Name: sqrl
Version: 0.2.0
Summary: a lightweight sqlite API that can do just about everything you need and allows you to fill in any gaps
Author-email: Oliver <oliverbcontact@gmail.com>
Project-URL: Homepage, https://github.com/olivesnake/sqrl
Project-URL: Issues, https://github.com/olivesnake/sqrl/issues
Classifier: Programming Language :: Python :: 3
Classifier: Operating System :: OS Independent
Requires-Python: >=3.8
License-File: LICENSE
